nonebot_plugin_qrcode/__init__.py
nonebot_plugin_qrcode/data_source.py
nonebot_plugin_qrcode-0.1.0.dist-info/LICENSE
nonebot_plugin_qrcode-0.1.0.dist-info/METADATA
nonebot_plugin_qrcode-0.1.0.dist-info/WHEEL
nonebot_plugin_qrcode-0.1.0.dist-info/top_level.txt
nonebot_plugin_qrcode-0.1.0.dist-info/RECORD
