Metadata-Version: 2.2
Name: nonebot-plugin-qrcode
Version: 0.1.0
Summary: QQ聊天二维码插件
Author-email: kexue <x@kexue-cloud.cn>, Eilles <EillesWan@outlook.com>
License: MIT License
Project-URL: homepage, https://github.com/kexue-z/nonebot-plugin-qrcode
Requires-Python: >=3.10
License-File: LICENSE
Requires-Dist: arclet-alconna>=1.8.32
Requires-Dist: arclet-alconna-tools>=0.7.10
Requires-Dist: httpx<0.28.0,>=0.27.0
Requires-Dist: nonebot-adapter-onebot>=2.4.6
Requires-Dist: nonebot-plugin-alconna>=0.53.1
Requires-Dist: nonebot-plugin-waiter>=0.8.0
Requires-Dist: nonebot2>=2.4.0
Requires-Dist: pillow>=11.0.0
Requires-Dist: pyzbar-x>=0.2.1
Requires-Dist: qrcode>=8.0
